{
	"astFolder": {
		"children": [
		],
		"path": "/Users/utilisateur/Documents/perso_gilles_fabre/projets/genese/genese/src/complexity/core/mocks/",
		"astFiles": [
			{
				"name": "debug.mock.ts",
				"text": "\n\n\nexport class DebugMock  {\n\n    opened;\n    setVersionSelected;\n\n\n    /**\n     * Initialization\n     */\n    ngOnInit() {\n        // ---\n        setTimeout(() => this.opened = true);\n        this.setVersionSelected();\n    }\n}\n",
				"astNode": {
					"children": [
						{
							"end": 226,
							"kind": "ClassDeclaration",
							"name": "DebugMock",
							"pos": 0,
							"start": 3,
							"children": [
								{
									"end": 9,
									"kind": "ExportKeyword",
									"pos": 0,
									"start": 3,
									"children": [
									]
								},
								{
									"end": 25,
									"kind": "Identifier",
									"name": "DebugMock",
									"pos": 15,
									"start": 16,
									"children": [
									]
								},
								{
									"end": 41,
									"kind": "PropertyDeclaration",
									"pos": 28,
									"start": 34,
									"children": [
										{
											"end": 40,
											"kind": "Identifier",
											"name": "opened",
											"pos": 28,
											"start": 34,
											"children": [
											]
										}
									]
								},
								{
									"end": 65,
									"kind": "PropertyDeclaration",
									"pos": 41,
									"start": 46,
									"children": [
										{
											"end": 64,
											"kind": "Identifier",
											"name": "setVersionSelected",
											"pos": 41,
											"start": 46,
											"children": [
											]
										}
									]
								},
								{
									"end": 224,
									"kind": "MethodDeclaration",
									"name": "ngOnInit",
									"pos": 65,
									"start": 110,
									"children": [
										{
											"end": 118,
											"kind": "Identifier",
											"name": "ngOnInit",
											"pos": 65,
											"start": 110,
											"children": [
											]
										},
										{
											"end": 224,
											"kind": "Block",
											"pos": 120,
											"start": 121,
											"children": [
												{
													"end": 183,
													"kind": "ExpressionStatement",
													"pos": 122,
													"start": 146,
													"children": [
														{
															"end": 182,
															"kind": "CallExpression",
															"pos": 122,
															"start": 146,
															"children": [
																{
																	"end": 156,
																	"kind": "Identifier",
																	"name": "setTimeout",
																	"pos": 122,
																	"start": 146,
																	"children": [
																	]
																},
																{
																	"end": 181,
																	"kind": "ArrowFunction",
																	"pos": 157,
																	"start": 157,
																	"children": [
																		{
																			"end": 162,
																			"kind": "EqualsGreaterThanToken",
																			"pos": 159,
																			"start": 160,
																			"children": [
																			]
																		},
																		{
																			"end": 181,
																			"kind": "BinaryExpression",
																			"pos": 162,
																			"start": 163,
																			"children": [
																				{
																					"end": 174,
																					"kind": "PropertyAccessExpression",
																					"pos": 162,
																					"start": 163,
																					"children": [
																						{
																							"end": 167,
																							"kind": "ThisKeyword",
																							"pos": 162,
																							"start": 163,
																							"children": [
																							]
																						},
																						{
																							"end": 174,
																							"kind": "Identifier",
																							"name": "opened",
																							"pos": 168,
																							"start": 168,
																							"children": [
																							]
																						}
																					]
																				},
																				{
																					"end": 176,
																					"kind": "FirstAssignment",
																					"pos": 174,
																					"start": 175,
																					"children": [
																					]
																				},
																				{
																					"end": 181,
																					"kind": "TrueKeyword",
																					"pos": 176,
																					"start": 177,
																					"children": [
																					]
																				}
																			]
																		}
																	]
																}
															]
														}
													]
												},
												{
													"end": 218,
													"kind": "ExpressionStatement",
													"pos": 183,
													"start": 192,
													"children": [
														{
															"end": 217,
															"kind": "CallExpression",
															"pos": 183,
															"start": 192,
															"children": [
																{
																	"end": 215,
																	"kind": "PropertyAccessExpression",
																	"pos": 183,
																	"start": 192,
																	"children": [
																		{
																			"end": 196,
																			"kind": "ThisKeyword",
																			"pos": 183,
																			"start": 192,
																			"children": [
																			]
																		},
																		{
																			"end": 215,
																			"kind": "Identifier",
																			"name": "setVersionSelected",
																			"pos": 197,
																			"start": 197,
																			"children": [
																			]
																		}
																	]
																}
															]
														}
													]
												}
											]
										}
									]
								}
							]
						},
						{
							"end": 227,
							"kind": "EndOfFileToken",
							"pos": 226,
							"start": 227,
							"children": [
							]
						}
					]
				}
			}
		]
	}
}